python_selvpcclient-1.0.0.dist-info/METADATA
python_selvpcclient-1.0.0.dist-info/RECORD
python_selvpcclient-1.0.0.dist-info/WHEEL
python_selvpcclient-1.0.0.dist-info/entry_points.txt
python_selvpcclient-1.0.0.dist-info/pbr.json
python_selvpcclient-1.0.0.dist-info/top_level.txt
selvpcclient/__init__.py
selvpcclient/base.py
selvpcclient/client.py
selvpcclient/formatters.py
selvpcclient/httpclient.py
selvpcclient/shell.py
selvpcclient/util.py
selvpcclient/commands/__init__.py
selvpcclient/commands/capabilities.py
selvpcclient/commands/floatingips.py
selvpcclient/commands/license.py
selvpcclient/commands/limit.py
selvpcclient/commands/project.py
selvpcclient/commands/quotas.py
selvpcclient/commands/role.py
selvpcclient/commands/subnet.py
selvpcclient/commands/token.py
selvpcclient/commands/user.py
selvpcclient/commands/vrrp.py
selvpcclient/exceptions/__init__.py
selvpcclient/exceptions/base.py
selvpcclient/exceptions/http.py
selvpcclient/resources/__init__.py
selvpcclient/resources/capabilities.py
selvpcclient/resources/floatingips.py
selvpcclient/resources/licenses.py
selvpcclient/resources/projects.py
selvpcclient/resources/quotas.py
selvpcclient/resources/roles.py
selvpcclient/resources/subnets.py
selvpcclient/resources/tokens.py
selvpcclient/resources/users.py
selvpcclient/resources/vrrp.py
tests/cli/__init__.py
tests/cli/test_capabilities.py
tests/cli/test_floatingip.py
tests/cli/test_license.py
tests/cli/test_limit.py
tests/cli/test_project.py
tests/cli/test_quota.py
tests/cli/test_role.py
tests/cli/test_subnet.py
tests/cli/test_token.py
tests/cli/test_user.py
tests/cli/test_vrrp.py
tests/rest/__init__.py
tests/rest/test_capabilities.py
tests/rest/test_floatingips.py
tests/rest/test_licenses.py
tests/rest/test_projects.py
tests/rest/test_quotas.py
tests/rest/test_roles.py
tests/rest/test_subnets.py
tests/rest/test_tokens.py
tests/rest/test_users.py
tests/rest/test_vrrp.py
tests/util/__init__.py
tests/util/answers.py
tests/util/params.py
